RunPredictor/__init__.py
RunPredictor/predict.py
runpredictor-1.0.dist-info/LICENSE.txt
runpredictor-1.0.dist-info/METADATA
runpredictor-1.0.dist-info/WHEEL
runpredictor-1.0.dist-info/top_level.txt
runpredictor-1.0.dist-info/RECORD
