Metadata-Version: 2.1
Name: runpredictor
Version: 1.0
Summary: A library predicting first innings score in odi,t-20 and ipl
Home-page: https://github.com/codophobia/RunPredictor
Author: Shivam Mitra
Author-email: shivamm389@gmail.com
License: GPLv2
Download-URL: https://github.com/codophobia/RunPredictor/tarball/1.0
Keywords: cricket,prediction
Platform: UNKNOWN
Requires-Dist: numpy
Requires-Dist: sklearn
